live_agent_sdk/__init__.py
live_agent_sdk/agent_client.py
live_agent_sdk/agent_config.py
live_agent_sdk/audio_pcm_data.py
plaud_live_agent_sdk-1.0.1.dist-info/METADATA
plaud_live_agent_sdk-1.0.1.dist-info/WHEEL
plaud_live_agent_sdk-1.0.1.dist-info/top_level.txt
plaud_live_agent_sdk-1.0.1.dist-info/RECORD
