Metadata-Version: 2.4
Name: plaud-live-agent-sdk
Version: 1.0.1
Summary: Plaud Live Agent SDK - 实时AI助手客户端SDK
Home-page: https://github.com/plaud-ai/plaud-live-agent-dev
Author: Plaud AI
Author-email: Plaud AI <dev-support@plaud.ai>
Maintainer-email: Plaud AI <dev-support@plaud.ai>
License-Expression: MIT
Project-URL: Homepage, https://github.com/Plaud-AI/plaud-live-agent-dev
Project-URL: Documentation, https://github.com/Plaud-AI/plaud-live-agent-dev/blob/main/README.md
Project-URL: Repository, https://github.com/Plaud-AI/plaud-live-agent-dev
Project-URL: Bug Tracker, https://github.com/Plaud-AI/plaud-live-agent-dev/issues
Keywords: Plaud,livekit,webrtc,audio,real-time,ai,assistant
Classifier: Development Status :: 4 - Beta
Classifier: Intended Audience :: Developers
Classifier: Operating System :: OS Independent
Classifier: Programming Language :: Python :: 3
Classifier: Programming Language :: Python :: 3.8
Classifier: Programming Language :: Python :: 3.9
Classifier: Programming Language :: Python :: 3.10
Classifier: Programming Language :: Python :: 3.11
Classifier: Topic :: Communications :: Chat
Classifier: Topic :: Multimedia :: Sound/Audio
Classifier: Topic :: Software Development :: Libraries :: Python Modules
Requires-Python: >=3.8
Requires-Dist: livekit>=1.0.0
Requires-Dist: livekit-api>=1.0.0
Requires-Dist: numpy>=1.20.0
Provides-Extra: dev
Requires-Dist: pytest>=6.0; extra == "dev"
Requires-Dist: pytest-asyncio>=0.18.0; extra == "dev"
Requires-Dist: black>=21.0; extra == "dev"
Requires-Dist: flake8>=3.8; extra == "dev"
Provides-Extra: audio
Requires-Dist: sounddevice>=0.4.0; extra == "audio"
Dynamic: author
Dynamic: home-page
Dynamic: requires-python
